ctbl_tools/__init__.py
ctbl_tools/config.py
ctbl_tools/exceptions.py
ctbl_tools/git.py
ctbl_tools/process.py
ctbl_tools-0.1.8.dist-info/METADATA
ctbl_tools-0.1.8.dist-info/WHEEL
ctbl_tools-0.1.8.dist-info/licenses/LICENSE
ctbl_tools-0.1.8.dist-info/RECORD
