Metadata-Version: 2.3
Name: ctbl_tools
Version: 0.1.8
Summary: A set of helpers classes for daily tasks: a reusable config file, a process helper, and a git interface.
Author-email: Cristian Bravo Lillo <cristian.bravo@gmail.com>
License: MIT
Classifier: Development Status :: 3 - Alpha
Classifier: Environment :: Console
Classifier: License :: OSI Approved :: MIT License
Classifier: Operating System :: POSIX :: Linux
Classifier: Programming Language :: Python :: 3.8
Classifier: Topic :: Utilities
Requires-Python: >=3.8
